{
  "_schema_version": "3",
  "_cluster": "mainnet",
  "_provider": "switchboard",
  "_note": "release/39 canonical Switchboard on-demand MAINNET feed map. adrena_feed_id range 142..255 reserved for Switchboard (see adrena/programs/adrena/src/state/pool.rs OracleProvider::feed_id_range). Crypto block 142-147 mirrors ChaosLabs (0-5) order: SOL, jitoSOL, BTC, WBTC, BONK, USDC. Slots 143/144/146/147 are Adrena-owned feeds on the mainnet on-demand queue. Slots 142 (SOLUSD) and 145 (WBTCUSD) currently reference BORROWED public-queue feed hashes pending Adrena-owned replacements \u2014 see `_source` on each entry. Swap-to-Adrena-owned is a pure config edit here + consumer pin bump, no program change required. Queue A43DyUGA7s8eXPxqEjJY6EBu1KKbNgfxF8h17VAHn13w is the on-demand mainnet default.",
  "_queue": "A43DyUGA7s8eXPxqEjJY6EBu1KKbNgfxF8h17VAHn13w",
  "switchboard_feed_map": [
    {
      "adrena_feed_id": 142,
      "symbol": "SOLUSD",
      "switchboard_feed_hash": "f9e1c461c1b2e4304f23fe537655f65691537d37813fe97566dc3137c1165fbf",
      "_feed_address": "Ceveqpim1FJZfx9DPeFDVDSz2HJavUqPPEJtZ2osNEmS",
      "_source": "BORROWED_PUBLIC_FEED \u2014 not Adrena-owned. Sourced from Switchboard mainnet explorer. Adrena-owned feed TBD; swap via adrena-abi config edit + pin bump when ready (no program change required)."
    },
    {
      "adrena_feed_id": 143,
      "symbol": "JITOSOLUSD",
      "switchboard_feed_hash": "cfa7308a1bf3291226c8df6eb288812c3beaffc614fce15146096d318dd1f3a6",
      "_feed_address": "8uTYSufNFNUsjhBQ9bzX4GVBesPbP73eJnoRyUGepxy1"
    },
    {
      "adrena_feed_id": 144,
      "symbol": "BTCUSD",
      "switchboard_feed_hash": "45bd1d1666cf259c85e890f59b4abb64504567d2d4d973ca417554a9aa5feb38",
      "_feed_address": "9bnTvExDE51oez37qmiUrJd21VePYvsC8JLmCxGBhT2B"
    },
    {
      "adrena_feed_id": 145,
      "symbol": "WBTCUSD",
      "switchboard_feed_hash": "88dbaf544a2a692eda2107e3cc1d46d6ca0111b748b6d9faec73c71c41f5199d",
      "_feed_address": "5a5DHgdv8KoRW9tGcePNao1QNJhsh9ZDnJDCBftGoTMk",
      "_source": "BORROWED_PUBLIC_FEED \u2014 not Adrena-owned. Sourced from Switchboard mainnet explorer. Adrena-owned feed TBD; swap via adrena-abi config edit + pin bump when ready (no program change required)."
    },
    {
      "adrena_feed_id": 146,
      "symbol": "BONKUSD",
      "switchboard_feed_hash": "efc3feb6353478af641540457ca7e7a778e7dddb446f436d6bad7e15d809010c",
      "_feed_address": "4MULkeCpERgxU94HPFaBeM2kmwYjbM3iHfsvSXxyjAs7"
    },
    {
      "adrena_feed_id": 147,
      "symbol": "USDCUSD",
      "switchboard_feed_hash": "6795044f45a4f3089f90fc79bd27bb29b3102760519640139df1473ad4f7791e",
      "_feed_address": "4cHYyQNZdrpDkCyw8eHcGXs7K6QyC5uQpj5YeM74mwCJ"
    }
  ]
}
